pretix_mpesa/__init__.py
pretix_mpesa/apps.py
pretix_mpesa/models.py
pretix_mpesa/payment.py
pretix_mpesa/signals.py
pretix_mpesa/tasks.py
pretix_mpesa/urls.py
pretix_mpesa/views.py
pretix_mpesa/locale/de/LC_MESSAGES/django.mo
pretix_mpesa/locale/de/LC_MESSAGES/django.po
pretix_mpesa/locale/de_Informal/.gitkeep
pretix_mpesa/locale/de_Informal/LC_MESSAGES/django.mo
pretix_mpesa/locale/de_Informal/LC_MESSAGES/django.po
pretix_mpesa/migrations/0001_initial.py
pretix_mpesa/migrations/0002_auto_20180919_1853.py
pretix_mpesa/migrations/0003_auto_20180919_1911.py
pretix_mpesa/migrations/__init__.py
pretix_mpesa/static/pretix_mpesa/.gitkeep
pretix_mpesa/templates/pretix_mpesa/.gitkeep
pretix_mpesa/templates/pretix_mpesa/checkout_payment_confirm.html
pretix_mpesa/templates/pretix_mpesa/checkout_payment_form.html
pretix_mpesa/templates/pretix_mpesa/pending.html
pretix_mpesa-1.0.5.dist-info/licenses/LICENSE
pretix_mpesa-1.0.5.dist-info/METADATA
pretix_mpesa-1.0.5.dist-info/WHEEL
pretix_mpesa-1.0.5.dist-info/entry_points.txt
pretix_mpesa-1.0.5.dist-info/top_level.txt
pretix_mpesa-1.0.5.dist-info/RECORD
