Metadata-Version: 2.4
Name: pretix_mpesa
Version: 1.0.5
Summary: Adds safaricom mpesa payments to pretix
Home-page: https://github.com/enyachoke/pretix-mpesa
Author: Joakim Bwire
Author-email: joakim.bwire@gmail.com
License: Apache Software License
License-File: LICENSE
Requires-Dist: phonenumbers
Requires-Dist: pympesa
Dynamic: author
Dynamic: author-email
Dynamic: description
Dynamic: home-page
Dynamic: license
Dynamic: license-file
Dynamic: requires-dist
Dynamic: summary
